{"nazivObrasca": "IZ-D-IP", "vrstaIzbora": "IZBOR OP\u0106INSKOG NA\u010cELNIKA OP\u0106INE PAKO\u0160TANE", "nazivObveznika": "ANTONIO LOKIN", "adresa": "PAKO\u0160TANE, VELEBITSKA ULICA 12", "oib": "94788070599", "brojPosebnogRacuna": "HR7524020063500029696", "vrstaIzvjesca": "IZVJE\u0160\u0106E O PRIMLJENIM DONACIJAMA ZA FINANCIRANJE IZBORNE PROMID\u017dBE", "razdobljeOd": "28.04.2021.", "razdobljeDo": "09.06.2021.", "datumSastavljanja": "09.06.2021.", "data": [], "ukupno": 0, "izbori": "GRADONA\u010cELNIK / OP\u0106INSKI NA\u010cELNIK", "mjesto": "PAKO\u0160TANE", "zupanija": "ZADARSKA \u017dUPANIJA"}