{"nazivObrasca": "IZ-D-IP", "vrstaIzbora": "IZBOR OP\u0106INSKOG NA\u010cELNIKA OP\u0106INE DEKANOVEC", "nazivObveznika": "IVAN HAJDAROVI\u0106", "adresa": "DEKANOVEC, KALNI\u010cKA ULICA 24", "oib": "85249333402", "brojPosebnogRacuna": "HR9023400093511040097", "vrstaIzvjesca": "IZVJE\u0160\u0106E O PRIMLJENIM DONACIJAMA ZA FINANCIRANJE IZBORNE PROMID\u017dBE", "razdobljeOd": "19.04.2021.", "razdobljeDo": "14.06.2021.", "datumSastavljanja": "14.06.2021.", "data": [], "ukupno": 0, "izbori": "GRADONA\u010cELNIK / OP\u0106INSKI NA\u010cELNIK", "mjesto": "DEKANOVEC", "zupanija": "ME\u0110IMURSKA \u017dUPANIJA"}