{"nazivObrasca": "IZ-D-IP", "vrstaIzbora": "IZBOR GRADONA\u010cELNIKA GRADA CRESA", "nazivObveznika": "SANJA TOMI\u0106", "adresa": "CRES, SVETI SIDAR 18", "oib": "82590470051", "brojPosebnogRacuna": "HR9124020063500026013", "vrstaIzvjesca": "IZVJE\u0160\u0106E O PRIMLJENIM DONACIJAMA ZA FINANCIRANJE IZBORNE PROMID\u017dBE", "razdobljeOd": "16.04.2021.", "razdobljeDo": "30.06.2021.", "datumSastavljanja": "30.06.2021.", "data": [], "ukupno": 0, "izbori": "GRADONA\u010cELNIK / OP\u0106INSKI NA\u010cELNIK", "mjesto": "CRES", "zupanija": "PRIMORSKO-GORANSKA \u017dUPANIJA"}