{"nazivObrasca": "IZ-D-IP", "vrstaIzbora": "IZBOR GRADONA\u010cELNIKA GRADA MALOG LO\u0160INJA", "nazivObveznika": "ANA KU\u010cI\u0106", "adresa": "MALI LO\u0160INJ, STJEPANA RADI\u0106A 19", "oib": "07579617542", "brojPosebnogRacuna": "HR3923400093511036068", "vrstaIzvjesca": "IZVJE\u0160\u0106E O PRIMLJENIM DONACIJAMA ZA FINANCIRANJE IZBORNE PROMID\u017dBE", "razdobljeOd": "08.04.2021.", "razdobljeDo": "29.06.2021.", "datumSastavljanja": "29.06.2021.", "data": [{"rb": "1", "nazivDonatora": "BISTRA d.o.o.", "oib": "54591734025", "adresaDonatora": "Antuna Radi\u0107a 8c, \u0110ur\u0111evac", "datumDonacije": "16.04.2021", "iznos": 20000.0, "trzisnaVrijednost": 0.0, "ukupno": 20000.0}, {"rb": "2", "nazivDonatora": "INGEMAR d.o.o.", "oib": "88706672580", "adresaDonatora": "Ba\u0161tijanova 7g, Rijeka", "datumDonacije": "20.04.2021", "iznos": 0.0, "trzisnaVrijednost": 25012.5, "ukupno": 25012.5}, {"rb": "3", "nazivDonatora": "ADING PROJEKT d.o.o. ZA GRADITELJSTVO", "oib": "23194084178", "adresaDonatora": "Pe\u0161\u0107anska 0176, Zagreb", "datumDonacije": "03.05.2021", "iznos": 5000.0, "trzisnaVrijednost": 0.0, "ukupno": 5000.0}, {"rb": "4", "nazivDonatora": "\u0160efik Mustedanagi\u0107", "oib": "75031330980", "adresaDonatora": "", "datumDonacije": "03.05.2021", "iznos": 4000.0, "trzisnaVrijednost": 0.0, "ukupno": 4000.0}, {"rb": "5", "nazivDonatora": "Dominik Ga\u0161pi\u0107", "oib": "97897406045", "adresaDonatora": "", "datumDonacije": "10.05.2021", "iznos": 5000.0, "trzisnaVrijednost": 0.0, "ukupno": 5000.0}], "ukupno": 59012.5, "izbori": "GRADONA\u010cELNIK / OP\u0106INSKI NA\u010cELNIK", "mjesto": "MALI LO\u0160INJ", "zupanija": "PRIMORSKO-GORANSKA \u017dUPANIJA"}