{"nazivObrasca": "IZ-D-IP", "vrstaIzbora": "IZBOR ZAMJENIKA \u017dUPANA PO\u017dE\u0160KO-SLAVONSKE \u017dUPANIJE IZ REDA PRIPADNIKA SRPSKE NACIONALNE MANJINE", "nazivObveznika": "TAMARA PUA\u010c", "adresa": "PO\u017dEGA, FRANKOPANSKA 53", "oib": "73766129123", "brojPosebnogRacuna": "HR6523400093511046367", "vrstaIzvjesca": "IZVJE\u0160\u0106E O PRIMLJENIM DONACIJAMA ZA FINANCIRANJE IZBORNE PROMID\u017dBE", "razdobljeOd": "29.04.2021.", "razdobljeDo": "15.06.2021.", "datumSastavljanja": "15.06.2021.", "data": [], "ukupno": 0, "izbori": "ZAMJENIK \u017dUPANA (srpska n.m.)", "mjesto": "BRESTOVAC", "zupanija": "PO\u017dE\u0160KO-SLAVONSKA \u017dUPANIJA"}