{"nazivObrasca": "IZ-D-IP", "vrstaIzbora": "IZBOR GRADONA\u010cELNIKA GRADA KA\u0160TELA", "nazivObveznika": "DRA\u0160KO KULI\u0160", "adresa": "KA\u0160TEL LUK\u0160I\u0106, MAJURINA 44", "oib": "54964496131", "brojPosebnogRacuna": "HR5024020063500029758", "vrstaIzvjesca": "IZVJE\u0160\u0106E O PRIMLJENIM DONACIJAMA ZA FINANCIRANJE IZBORNE PROMID\u017dBE", "razdobljeOd": "28.04.2021.", "razdobljeDo": "20.05.2021.", "datumSastavljanja": "20.05.2021.", "data": [], "ukupno": 0, "izbori": "GRADONA\u010cELNIK / OP\u0106INSKI NA\u010cELNIK", "mjesto": "KA\u0160TELA", "zupanija": "SPLITSKO-DALMATINSKA \u017dUPANIJA"}