{"nazivObrasca": "IZ-D-IP", "vrstaIzbora": "IZBOR OP\u0106INSKOG NA\u010cELNIKA OP\u0106INE KLO\u0160TAR PODRAVSKI", "nazivObveznika": "SINI\u0160A PAVLOVI\u0106", "adresa": "BUDAN\u010cEVICA, LIVADSKA 7", "oib": "31372592725", "brojPosebnogRacuna": "HR7824020063500027993", "vrstaIzvjesca": "IZVJE\u0160\u0106E O PRIMLJENIM DONACIJAMA ZA FINANCIRANJE IZBORNE PROMID\u017dBE", "razdobljeOd": "22.04.2021.", "razdobljeDo": "15.06.2021.", "datumSastavljanja": "15.06.2021.", "data": [{"rb": "1", "nazivDonatora": "BISTRA D.O.O.", "oib": "54591734025", "adresaDonatora": "A.RADI\u0106A 8C, \u0110UR\u0110EVAC", "datumDonacije": "23.04.2021", "iznos": 10000.0, "trzisnaVrijednost": 0.0, "ukupno": 10000.0}, {"rb": "2", "nazivDonatora": "USLUGE SIGMA D.O.O.", "oib": "31388115556", "adresaDonatora": "LONJI\u010cKA 2A, ZAGREB", "datumDonacije": "23.04.2021", "iznos": 1000.0, "trzisnaVrijednost": 0.0, "ukupno": 1000.0}, {"rb": "3", "nazivDonatora": "IVAN KOREN", "oib": "15104115306", "adresaDonatora": "", "datumDonacije": "27.04.2021", "iznos": 1000.0, "trzisnaVrijednost": 0.0, "ukupno": 1000.0}, {"rb": "4", "nazivDonatora": "KARAS PROIZVODNJA D.O.O.", "oib": "03684750352", "adresaDonatora": "SUHARA 9, KOZAREVAC", "datumDonacije": "04.05.2021", "iznos": 1000.0, "trzisnaVrijednost": 0.0, "ukupno": 1000.0}, {"rb": "5", "nazivDonatora": "PRAJO BETON D.O.O.", "oib": "91875708484", "adresaDonatora": "LUKA\u010c 1, LUKA\u010c", "datumDonacije": "04.05.2021", "iznos": 5000.0, "trzisnaVrijednost": 0.0, "ukupno": 5000.0}, {"rb": "6", "nazivDonatora": "Elektro \u0160ok d.o.o.", "oib": "53142143575", "adresaDonatora": "Petra Preradovi\u0107a 116 Podravske Sesvete, Podravske Sesvete", "datumDonacije": "10.05.2021", "iznos": 500.0, "trzisnaVrijednost": 0.0, "ukupno": 500.0}], "ukupno": 18500.0, "izbori": "GRADONA\u010cELNIK / OP\u0106INSKI NA\u010cELNIK", "mjesto": "KLO\u0160TAR PODRAVSKI", "zupanija": "KOPRIVNI\u010cKO-KRI\u017dEVA\u010cKA \u017dUPANIJA"}