{"nazivObrasca": "IZ-D-IP", "vrstaIzbora": "IZBOR OP\u0106INSKOG NA\u010cELNIKA OP\u0106INE DRAGALI\u0106", "nazivObveznika": "ZVONIMIR KARLIK", "adresa": "DRAGALI\u0106, TRG SV. IVANA KRSTITELJA 13", "oib": "25412512677", "brojPosebnogRacuna": "HR3723600003510287502", "vrstaIzvjesca": "IZVJE\u0160\u0106E O PRIMLJENIM DONACIJAMA ZA FINANCIRANJE IZBORNE PROMID\u017dBE", "razdobljeOd": "15.04.2021.", "razdobljeDo": "13.06.2021.", "datumSastavljanja": "13.06.2021.", "data": [], "ukupno": 0, "izbori": "GRADONA\u010cELNIK / OP\u0106INSKI NA\u010cELNIK", "mjesto": "DRAGALI\u0106", "zupanija": "BRODSKO-POSAVSKA \u017dUPANIJA"}