{"nazivObrasca": "IZ-D-IP", "vrstaIzbora": "IZBOR OP\u0106INSKOG NA\u010cELNIKA OP\u0106INE ORIOVAC", "nazivObveznika": "JELENA IVEZI\u0106", "adresa": "RADOVANJE, ULICA RADOVANJE 2A", "oib": "90622094301", "brojPosebnogRacuna": "HR6923600003510212527", "vrstaIzvjesca": "IZVJE\u0160\u0106E O PRIMLJENIM DONACIJAMA ZA FINANCIRANJE IZBORNE PROMID\u017dBE", "razdobljeOd": "11.03.2021.", "razdobljeDo": "25.06.2021.", "datumSastavljanja": "25.06.2021.", "data": [{"rb": "1", "nazivDonatora": "ANTONIJA SANDA\u0106", "oib": "63964308962", "adresaDonatora": "", "datumDonacije": "07.04.2021", "iznos": 200.0, "trzisnaVrijednost": 0.0, "ukupno": 200.0}, {"rb": "2", "nazivDonatora": "MARIJA RE\u017dAN", "oib": "51655061068", "adresaDonatora": "", "datumDonacije": "07.04.2021", "iznos": 300.0, "trzisnaVrijednost": 0.0, "ukupno": 300.0}, {"rb": "3", "nazivDonatora": "VJEKOSLAV LOKICA", "oib": "05806724893", "adresaDonatora": "", "datumDonacije": "07.04.2021", "iznos": 200.0, "trzisnaVrijednost": 0.0, "ukupno": 200.0}, {"rb": "4", "nazivDonatora": "\u017dANA LELAS", "oib": "21387625298", "adresaDonatora": "", "datumDonacije": "07.04.2021", "iznos": 100.0, "trzisnaVrijednost": 0.0, "ukupno": 100.0}, {"rb": "5", "nazivDonatora": "ANJA GIKIEWICZ", "oib": "07651786629", "adresaDonatora": "", "datumDonacije": "09.04.2021", "iznos": 300.0, "trzisnaVrijednost": 0.0, "ukupno": 300.0}, {"rb": "6", "nazivDonatora": "ANA SEMERIN", "oib": "82453323339", "adresaDonatora": "", "datumDonacije": "10.04.2021", "iznos": 200.0, "trzisnaVrijednost": 0.0, "ukupno": 200.0}, {"rb": "7", "nazivDonatora": "ANA VRSALJKO", "oib": "23311870331", "adresaDonatora": "", "datumDonacije": "12.04.2021", "iznos": 200.0, "trzisnaVrijednost": 0.0, "ukupno": 200.0}, {"rb": "8", "nazivDonatora": "MARTINA GAMBIRA\u017dA", "oib": "66244600472", "adresaDonatora": "", "datumDonacije": "12.04.2021", "iznos": 500.0, "trzisnaVrijednost": 0.0, "ukupno": 500.0}, {"rb": "9", "nazivDonatora": "OPG \u010cALDAREVI\u0106 ANITA", "oib": "19013389691", "adresaDonatora": "", "datumDonacije": "22.04.2021", "iznos": 2000.0, "trzisnaVrijednost": 0.0, "ukupno": 2000.0}, {"rb": "10", "nazivDonatora": "IVA BRKLJA\u010cA", "oib": "98551967887", "adresaDonatora": "", "datumDonacije": "26.04.2021", "iznos": 400.0, "trzisnaVrijednost": 0.0, "ukupno": 400.0}, {"rb": "11", "nazivDonatora": "ANA ZEBI\u0106", "oib": "94640444712", "adresaDonatora": "", "datumDonacije": "27.04.2021", "iznos": 100.0, "trzisnaVrijednost": 0.0, "ukupno": 100.0}], "ukupno": 4500.0, "izbori": "GRADONA\u010cELNIK / OP\u0106INSKI NA\u010cELNIK", "mjesto": "ORIOVAC", "zupanija": "BRODSKO-POSAVSKA \u017dUPANIJA"}