{"nazivObrasca": "IZ-D-IP", "vrstaIzbora": "IZBOR OP\u0106INSKOG NA\u010cELNIKA OP\u0106INE VELIKA TRNOVITICA", "nazivObveznika": "VLATKO KRAJA\u010cI\u0106", "adresa": "GORNJA PLO\u0160\u010cICA, GORNJA PLO\u0160\u010cICA 16", "oib": "36057700530", "brojPosebnogRacuna": "HR5823400093511044068", "vrstaIzvjesca": "IZVJE\u0160\u0106E O PRIMLJENIM DONACIJAMA ZA FINANCIRANJE IZBORNE PROMID\u017dBE", "razdobljeOd": "27.04.2021.", "razdobljeDo": "13.06.2021.", "datumSastavljanja": "13.06.2021.", "data": [], "ukupno": 0, "izbori": "GRADONA\u010cELNIK / OP\u0106INSKI NA\u010cELNIK", "mjesto": "VELIKA TRNOVITICA", "zupanija": "BJELOVARSKO-BILOGORSKA \u017dUPANIJA"}