{"nazivObrasca": "IZ-D-IP", "vrstaIzbora": "IZBOR GRADONA\u010cELNIKA GRADA VODNJANA - DIGNANO", "nazivObveznika": "BRUNO BULI\u0106", "adresa": "VODNJAN, GRADINA 3A", "oib": "06882047375", "brojPosebnogRacuna": "HR2923400093511045366", "vrstaIzvjesca": "IZVJE\u0160\u0106E O PRIMLJENIM DONACIJAMA ZA FINANCIRANJE IZBORNE PROMID\u017dBE", "razdobljeOd": "28.04.2021.", "razdobljeDo": "08.05.2021.", "datumSastavljanja": "08.05.2021.", "data": [], "ukupno": 0, "izbori": "GRADONA\u010cELNIK / OP\u0106INSKI NA\u010cELNIK", "mjesto": "VODNJAN - DIGNANO", "zupanija": "ISTARSKA \u017dUPANIJA"}