{"nazivObrasca": "IZ-D-IP", "vrstaIzbora": "IZBOR \u010cLANOVA GRADSKE SKUP\u0160TINE GRADA ZAGREBA", "nazivObveznika": "NEZAVISNA LISTA TOMISLAV STOJAK - NLTS", "adresa": "ZAGREB, MARTI\u0106EVA 33 B", "oib": "19904638939", "brojPosebnogRacuna": "HR3424020061500106841", "vrstaIzvjesca": "IZVJE\u0160\u0106E O PRIMLJENIM DONACIJAMA ZA FINANCIRANJE IZBORNE PROMID\u017dBE", "razdobljeOd": "23.04.2021.", "razdobljeDo": "03.06.2021.", "datumSastavljanja": "03.06.2021.", "data": [], "ukupno": 0, "izbori": "GRADSKA SKUP\u0160TINA", "mjesto": "GRAD ZAGREB", "zupanija": "GRAD ZAGREB"}