{"nazivObrasca": "IZ-D-IP", "vrstaIzbora": "IZBOR \u010cLANOVA GRADSKE SKUP\u0160TINE GRADA ZAGREBA", "nazivObveznika": "CENTAR", "adresa": "SPLIT, GUNDULI\u0106EVA 26A", "oib": "42956743890", "brojPosebnogRacuna": "HR9423900011500210461", "vrstaIzvjesca": "IZVJE\u0160\u0106E O PRIMLJENIM DONACIJAMA ZA FINANCIRANJE IZBORNE PROMID\u017dBE", "razdobljeOd": "08.04.2021.", "razdobljeDo": "15.06.2021.", "datumSastavljanja": "15.06.2021.", "data": [{"rb": "1", "nazivDonatora": "Kristijan Kolarec", "oib": "54992035560", "adresaDonatora": "", "datumDonacije": "19.04.2021", "iznos": 100.0, "trzisnaVrijednost": 0.0, "ukupno": 100.0}, {"rb": "2", "nazivDonatora": "Predrag Piljek", "oib": "44092044483", "adresaDonatora": "", "datumDonacije": "19.04.2021", "iznos": 200.0, "trzisnaVrijednost": 0.0, "ukupno": 200.0}, {"rb": "3", "nazivDonatora": "Barbara Salopek", "oib": "68816054868", "adresaDonatora": "", "datumDonacije": "27.04.2021", "iznos": 1000.0, "trzisnaVrijednost": 0.0, "ukupno": 1000.0}, {"rb": "4", "nazivDonatora": "Miroslav Mar\u0161", "oib": "63488609111", "adresaDonatora": "", "datumDonacije": "28.04.2021", "iznos": 400.0, "trzisnaVrijednost": 0.0, "ukupno": 400.0}, {"rb": "5", "nazivDonatora": "Mario \u017divi\u0107", "oib": "46884034219", "adresaDonatora": "", "datumDonacije": "04.05.2021", "iznos": 300.0, "trzisnaVrijednost": 0.0, "ukupno": 300.0}, {"rb": "6", "nazivDonatora": "Kristijan Kolarec", "oib": "54992035560", "adresaDonatora": "", "datumDonacije": "10.05.2021", "iznos": 100.0, "trzisnaVrijednost": 0.0, "ukupno": 100.0}, {"rb": "7", "nazivDonatora": "Milka \u0110uri\u0107 Cvetanovi\u0107", "oib": "64550383384", "adresaDonatora": "", "datumDonacije": "10.05.2021", "iznos": 1000.0, "trzisnaVrijednost": 0.0, "ukupno": 1000.0}], "ukupno": 3100.0, "izbori": "GRADSKA SKUP\u0160TINA", "mjesto": "GRAD ZAGREB", "zupanija": "GRAD ZAGREB"}