{"nazivObrasca": "IZ-D-IP", "vrstaIzbora": "IZBOR GRADONA\u010cELNIKA GRADA KLANJCA", "nazivObveznika": "NEDJELJKO BABI\u0106", "adresa": "LU\u010cELNICA TOMA\u0160EVE\u010cKA, LU\u010cELNICA TOMA\u0160EVE\u010cKA 54", "oib": "36229982276", "brojPosebnogRacuna": "HR2824020063500028505", "vrstaIzvjesca": "IZVJE\u0160\u0106E O PRIMLJENIM DONACIJAMA ZA FINANCIRANJE IZBORNE PROMID\u017dBE", "razdobljeOd": "23.04.2021.", "razdobljeDo": "07.06.2021.", "datumSastavljanja": "07.06.2021.", "data": [], "ukupno": 0, "izbori": "GRADONA\u010cELNIK / OP\u0106INSKI NA\u010cELNIK", "mjesto": "KLANJEC", "zupanija": "KRAPINSKO-ZAGORSKA \u017dUPANIJA"}