{"nazivObrasca": "IZ-D-IP", "vrstaIzbora": "IZBOR \u010cLANOVA GRADSKOG VIJE\u0106A GRADA OZLJA", "nazivObveznika": "HRVATSKA NARODNA STRANKA - LIBERALNI DEMOKRATI - HNS, HRVATSKA STRANKA UMIROVLJENIKA - HSU", "adresa": "ZAGREB, ULICA KNEZA MISLAVA 8", "oib": "82435880635", "brojPosebnogRacuna": "HR5524020061500105687", "vrstaIzvjesca": "IZVJE\u0160\u0106E O PRIMLJENIM DONACIJAMA ZA FINANCIRANJE IZBORNE PROMID\u017dBE", "razdobljeOd": "22.04.2021.", "razdobljeDo": "07.06.2021.", "datumSastavljanja": "07.06.2021.", "data": [], "ukupno": 0, "izbori": "GRADSKO / OP\u0106INSKO VIJE\u0106E", "mjesto": "OZALJ", "zupanija": "KARLOVA\u010cKA \u017dUPANIJA"}