{"nazivObrasca": "IZ-D-IP", "vrstaIzbora": "IZBOR GRADONA\u010cELNIKA GRADA DUBROVNIKA", "nazivObveznika": "\u017dELJKO RAGU\u017d", "adresa": "DUBROVNIK, KNEZA BRANIMIRA 2", "oib": "31123178134", "brojPosebnogRacuna": "HR5223600003510286165", "vrstaIzvjesca": "IZVJE\u0160\u0106E O PRIMLJENIM DONACIJAMA ZA FINANCIRANJE IZBORNE PROMID\u017dBE", "razdobljeOd": "07.04.2021.", "razdobljeDo": "15.06.2021.", "datumSastavljanja": "15.06.2021.", "data": [{"rb": "1", "nazivDonatora": "\u017dELJKO RAGU\u017d", "oib": "31123178134", "adresaDonatora": "", "datumDonacije": "07.04.2021", "iznos": 10000.0, "trzisnaVrijednost": 0.0, "ukupno": 10000.0}, {"rb": "2", "nazivDonatora": "IVANA \u0160EPAK", "oib": "99312472714", "adresaDonatora": "", "datumDonacije": "16.04.2021", "iznos": 10000.0, "trzisnaVrijednost": 0.0, "ukupno": 10000.0}, {"rb": "3", "nazivDonatora": "\u017dELJKO RAGU\u017d", "oib": "31123178134", "adresaDonatora": "", "datumDonacije": "23.04.2021", "iznos": 20000.0, "trzisnaVrijednost": 0.0, "ukupno": 20000.0}, {"rb": "4", "nazivDonatora": "PIZZA SHOP D.O.O.", "oib": "11862053788", "adresaDonatora": "KOMOLAC 11C, Dubrovnik", "datumDonacije": "04.05.2021", "iznos": 10000.0, "trzisnaVrijednost": 0.0, "ukupno": 10000.0}, {"rb": "5", "nazivDonatora": "MARKO MILJANI\u0106", "oib": "76284875660", "adresaDonatora": "", "datumDonacije": "14.05.2021", "iznos": 4000.0, "trzisnaVrijednost": 0.0, "ukupno": 4000.0}, {"rb": "6", "nazivDonatora": "ROBERTA PREBISALI\u0106", "oib": "26521890165", "adresaDonatora": "", "datumDonacije": "14.05.2021", "iznos": 1000.0, "trzisnaVrijednost": 0.0, "ukupno": 1000.0}], "ukupno": 55000.0, "izbori": "GRADONA\u010cELNIK / OP\u0106INSKI NA\u010cELNIK", "mjesto": "DUBROVNIK", "zupanija": "DUBROVA\u010cKO-NERETVANSKA \u017dUPANIJA"}