{"nazivObrasca": "IZ-D-IP", "vrstaIzbora": "IZBOR GRADONA\u010cELNIKA GRADA IVANI\u0106-GRADA", "nazivObveznika": "BORISLAV KOVA\u010cI\u0106", "adresa": "IVANI\u0106-GRAD, VUKOVARSKA ULICA 10", "oib": "94778375676", "brojPosebnogRacuna": "HR1023400093511039015", "vrstaIzvjesca": "IZVJE\u0160\u0106E O PRIMLJENIM DONACIJAMA ZA FINANCIRANJE IZBORNE PROMID\u017dBE", "razdobljeOd": "16.04.2021.", "razdobljeDo": "15.06.2021.", "datumSastavljanja": "15.06.2021.", "data": [], "ukupno": 0, "izbori": "GRADONA\u010cELNIK / OP\u0106INSKI NA\u010cELNIK", "mjesto": "IVANI\u0106-GRAD", "zupanija": "ZAGREBA\u010cKA \u017dUPANIJA"}