{"nazivObrasca": "IZ-D-IP", "vrstaIzbora": "IZBOR OP\u0106INSKOG NA\u010cELNIKA OP\u0106INE POKUPSKO", "nazivObveznika": "MARTINA POPOV\u010cI\u0106", "adresa": "HOTNJA, HOTNJA 50", "oib": "72826501763", "brojPosebnogRacuna": "HR7123600003510285726", "vrstaIzvjesca": "IZVJE\u0160\u0106E O PRIMLJENIM DONACIJAMA ZA FINANCIRANJE IZBORNE PROMID\u017dBE", "razdobljeOd": "02.04.2021.", "razdobljeDo": "14.06.2021.", "datumSastavljanja": "14.06.2021.", "data": [{"rb": "1", "nazivDonatora": "MB, Obrt za trgovinu, ugostiteljstvo i usluge vl. BRADI\u0106 MARIJAN", "oib": "43996111844", "adresaDonatora": "Hotnja, Hotnja 99, Hotnja", "datumDonacije": "14.05.2021", "iznos": 5000.0, "trzisnaVrijednost": 0.0, "ukupno": 5000.0}], "ukupno": 5000.0, "izbori": "GRADONA\u010cELNIK / OP\u0106INSKI NA\u010cELNIK", "mjesto": "POKUPSKO", "zupanija": "ZAGREBA\u010cKA \u017dUPANIJA"}