{"nazivObrasca": "IZ-D-IP", "vrstaIzbora": "IZBOR ZAMJENIKA OP\u0106INSKOG NA\u010cELNIKA OP\u0106INE GVOZD IZ REDA PRIPADNIKA HRVATSKOG NARODA", "nazivObveznika": "MARIJA ID\u017dAN", "adresa": "VRGINMOST, ANDRIJE HEBRANGA 14", "oib": "47901116302", "brojPosebnogRacuna": "HR6623600003513464021", "vrstaIzvjesca": "IZVJE\u0160\u0106E O PRIMLJENIM DONACIJAMA ZA FINANCIRANJE IZBORNE PROMID\u017dBE", "razdobljeOd": "23.04.2021.", "razdobljeDo": "09.06.2021.", "datumSastavljanja": "09.06.2021.", "data": [], "ukupno": 0, "izbori": "ZAMJENIK OP\u0106INSKOG NA\u010cELNIKA IZ REDA HRVATSKOG NARODA", "mjesto": "GVOZD", "zupanija": "SISA\u010cKO-MOSLAVA\u010cKA \u017dUPANIJA"}