{"nazivObrasca": "IZ-D-IP", "vrstaIzbora": "IZBOR ZAMJENIKA GRADONA\u010cELNIKA HRVATSKE KOSTAJNICE IZ REDA PRIPADNIKA SRPSKE NACIONALNE MANJINE", "nazivObveznika": "MILODRAG LJUBENKOVI\u0106", "adresa": "\u010cUKUR, \u010cUKUR 20", "oib": "74161450412", "brojPosebnogRacuna": "HR4923400093511042484", "vrstaIzvjesca": "IZVJE\u0160\u0106E O PRIMLJENIM DONACIJAMA ZA FINANCIRANJE IZBORNE PROMID\u017dBE", "razdobljeOd": "22.04.2021.", "razdobljeDo": "21.05.2021.", "datumSastavljanja": "21.05.2021.", "data": [], "ukupno": 0, "izbori": "ZAMJENIK GRADONA\u010cELNIKA / OP\u0106INSKOG NA\u010cELNIKA (srpska n.m.)", "mjesto": "HRVATSKA KOSTAJNICA", "zupanija": "SISA\u010cKO-MOSLAVA\u010cKA \u017dUPANIJA"}